{
  "fullWidth": 500,
  "fullHeight": 500,
  "styles": {
    "font": "arial.ttf",
    "justification": "center",
    "alignment": "middle",
    "textBaseline": "hanging"
  },
  "requirements": [],
  "elements": [
    {
      "type": "text",
      "name": "i",
      "styles": {
        "font": "belweb.ttf",
        "x": 0,
        "y": 0,
        "xSize": 500,
        "ySize": 500
      }
    }],
  "subTypes": [],
  "constants": {
    "->": {
      "text": "Է",
      "styles": {
        "font": "Aharoni-True.ttf"
      },
      "description": "yields"
    },
    "fire": {
      "text": "ե",
      "styles": {
        "font": "Aharoni-True.ttf",
        "innerShadow": {
          "styles": {
            "fillStyle": "#FF0",
            "initialLineWidth": 1,
            "strokeStyle": "#400",
            "shadowColor": "#f00",
            "secondLineWidth": 2
          }
        }
      }
    },
    "acid": {
      "text": "ӳ",
      "styles": {
        "font": "Aharoni-True.ttf",
        "innerShadow": {
          "styles": {
            "fillStyle": "#0F0",
            "initialLineWidth": 1,
            "strokeStyle": "#000",
            "shadowColor": "#FF0",
            "secondLineWidth": 2
          }
        }
      }
    },
    "bullets": {
      "text": "Ի",
      "styles": {
        "font": "Aharoni-True.ttf",
        "innerShadow": {
          "styles": {
            "fillStyle": "#999",
            "initialLineWidth": 1,
            "strokeStyle": "#000",
            "shadowColor": "#666",
            "secondLineWidth": 2
          }
        }
      }
    },
    "punch": {
      "text": "ӱ",
      "styles": {
        "font": "Aharoni-True.ttf",
        "innerShadow": {
          "styles": {
            "fillStyle": "#A86",
            "initialLineWidth": 1,
            "strokeStyle": "#000",
            "shadowColor": "#642",
            "secondLineWidth": 2
          }
        }
      }
    },
    "scratch": {
      "text": "Ӱ",
      "styles": {
        "font": "Aharoni-True.ttf",
        "innerShadow": {
          "styles": {
            "fillStyle": "#A21",
            "initialLineWidth": 1,
            "strokeStyle": "#000",
            "shadowColor": "#610",
            "secondLineWidth": 2
          }
        }
      }
    },
    "electricity": {
      "text": "ԧ",
      "styles": {
        "font": "Aharoni-True.ttf",
        "innerShadow": {
          "styles": {
            "fillStyle": "#ff0",
            "initialLineWidth": 1,
            "strokeStyle": "#000",
            "shadowColor": "#880",
            "secondLineWidth": 2
          }
        }
      }
    },
    "speed": {
      "text": "ӛ",
      "styles": {
        "font": "Aharoni-True.ttf",
        "color": "#ff0",
        "innerShadow": {
          "styles": {
            "fillStyle": "#ff0",
            "initialLineWidth": 1,
            "strokeStyle": "#000",
            "shadowColor": "#440",
            "secondLineWidth": 2
          }
        }
      }
    },
    "abominationCard": {
      "text": "ҵ",
      "styles": {
        "font": "Aharoni-True.ttf"
      }
    },
    "cyborgCard": {
      "text": "Ҷ",
      "styles": {
        "font": "Aharoni-True.ttf"
      }
    },
    "robotCard": {
      "text": "ҷ",
      "styles": {
        "font": "Aharoni-True.ttf"
      }
    },
    "ufoCard": {
      "text": "Ҹ",
      "styles": {
        "font": "Aharoni-True.ttf"
      }
    },
    "alienCard": {
      "text": "ҹ",
      "styles": {
        "font": "Aharoni-True.ttf"
      }
    },
    "plantCard": {
      "text": "Һ",
      "styles": {
        "font": "Aharoni-True.ttf"
      }
    },
    "foeCard": {
      "text": "ԗ",
      "styles": {
        "font": "Aharoni-True.ttf"
      }
    },
    "wildAttack": {
      "text": "Լ",
      "styles": {
        "font": "Aharoni-True.ttf"
      }
    },
    "wildAttack2": {
      "text": "ՂՂՂ",
      "styles": {
        "font": "Aharoni-True.ttf"
      }
    },
    "healing": {
      "text": "փ",
      "styles": {
        "font": "Aharoni-True.ttf",
        "innerShadow": {
          "styles": {
            "fillStyle": "#0f0",
            "initialLineWidth": 1,
            "strokeStyle": "#000",
            "shadowColor": "#080",
            "secondLineWidth": 2
          }
        }
      }
    },
    "yields": {
      "text": ":",
      "text.": "Է",
      "styles": {
        "font": "Aharoni-True.ttf"
      }
    },
    "flip": {
      "text": "ծ",
      "styles": {
        "font": "Aharoni-True.ttf"
      }
    },
    "damage": {
      "text": "Ӯ",
      "styles": {
        "font": "Aharoni-True.ttf",
        "maxFontSize": 10,
        "innerShadow": {
          "styles": {
            "fillStyle": "#f00",
            "initialLineWidth": 1,
            "strokeStyle": "#000",
            "shadowColor": "#ff0",
            "secondLineWidth": 2
          }
        }
      }
    },
    "attack": {
      "text": "Ղ",
      "styles": {
        "font": "Aharoni-True.ttf"
      }
    },
    "energy": {
      "text": "Ԩ",
      "styles": {
        "font": "Aharoni-True.ttf",
        "innerShadow": {
          "styles": {
            "fillStyle": "#FF0",
            "initialLineWidth": 1,
            "strokeStyle": "#000",
            "shadowColor": "#880",
            "secondLineWidth": 2
          }
        }
      }
    },
    "+energy": {
      "text": "ҳ",
      "styles": {
        "font": "Aharoni-True.ttf",
        "innerShadow": {
          "styles": {
            "fillStyle": "#0F0",
            "initialLineWidth": 1,
            "strokeStyle": "#000",
            "shadowColor": "#080",
            "secondLineWidth": 2
          }
        }
      }
    },
    "-energy": {
      "text": "Ҵ",
      "styles": {
        "font": "Aharoni-True.ttf",
        "innerShadow": {
          "styles": {
            "fillStyle": "#F00",
            "initialLineWidth": 1,
            "strokeStyle": "#000",
            "shadowColor": "#800",
            "secondLineWidth": 2
          }
        }
      }
    },
    "cost": {
      "text": "$",
      "styles": {}
    },
    "size": {
      "text": "դ",
      "styles": {
        "font": "Aharoni-True.ttf",
        "innerShadow": {
          "styles": {
            "fillStyle": "#00F",
            "initialLineWidth": 1,
            "strokeStyle": "#000",
            "shadowColor": "#008",
            "secondLineWidth": 2
          }
        }
      }
    },
    "repair": {
      "text": "ӭ",
      "styles": {
        "font": "Aharoni-True.ttf",
        "innerShadow": {
          "styles": {
            "fillStyle": "#0FF",
            "initialLineWidth": 1,
            "strokeStyle": "#000",
            "shadowColor": "#088",
            "secondLineWidth": 2
          }
        }
      }
    },
    "defense": {
      "text": "Ԡ",
      "styles": {
        "font": "Aharoni-True.ttf",
        "innerShadow": {
          "styles": {
            "fillStyle": "#800",
            "initialLineWidth": 1,
            "strokeStyle": "#000",
            "shadowColor": "#400",
            "secondLineWidth": 2
          }
        }
      }
    },
    "space": {
      "text": "ը",
      "styles": {
        "font": "Aharoni-True.ttf",
        "innerShadow": {
          "styles": {
            "fillStyle": "#00f",
            "initialLineWidth": 1,
            "strokeStyle": "#000",
            "shadowColor": "#008",
            "secondLineWidth": 2
          }
        }
      }
    }
  }
}